<?xml version="1.0" encoding="utf-8"?>
<lang_text xmlns:xsi="http://www.w3.org/2001/XMLSchema-instance" xmlns:xsd="http://www.w3.org/2001/XMLSchema">
  <code>en</code>
  <lang_text_entries>
  	<text_entry key="START">START</text_entry>
    <text_entry key="TOUCH_SCREEN">TOUCH THE SCREEN</text_entry>
    <text_entry key="TIMEOUT_WARNING">CAREFUL!&#13;&#10;TIME IS RUNNING OUT.</text_entry>
    <text_entry key="TIMEOUT_WARNING2">To start the game, hit the bag at shoulder height.</text_entry>
    <text_entry key="1P">ONE PLAYER</text_entry>
    <text_entry key="2P">TWO PLAYERS</text_entry>
    <text_entry key="P1TITLEKEY">PLAYER 1 / GREEN</text_entry>
    <text_entry key="P2TITLEKEY">PLAYER 2 / YELLOW</text_entry>
    <text_entry key="SCREEN1_TITLE">IT’S YOUR TURN TO BOX!</text_entry>
    <text_entry key="SCREEN1_CONTENT">Welcome to the boxing workshop.&#13;&#10;
The game consists in hitting the green area that appears on the bag with your fists.&#13;&#10;
Each successful punch increases your score. Your rapid response with your punch and the precision of your blow have a direct impact on your number of points.&#13;&#10;&#13;&#10;
To continue, touch the arrow.</text_entry>
    <text_entry key="SCREEN2_TITLE">NUMBER OF PLAYERS</text_entry>
    <text_entry key="SCREEN2_CONTENT">Choose one player or two players.</text_entry>
    <text_entry key="SCREEN3_TITLE">PARTICIPATION IN RESEARCH</text_entry>
    <text_entry key="Q1">Would you like to take part in research to improve the interactive punch bag?</text_entry>
    <text_entry key="Q1A1">YES</text_entry>
    <text_entry key="Q1A2">NO</text_entry>
    <text_entry key="Q2">YOUR AGE</text_entry>
    <text_entry key="Q2A1">&lt; 14</text_entry>
    <text_entry key="Q2A2">14 - 20</text_entry>
    <text_entry key="Q2A3">21 - 30</text_entry>
    <text_entry key="Q2A4">31 - 40</text_entry>
    <text_entry key="Q2A5">41 - 50</text_entry>
    <text_entry key="Q2A6">51 - 60</text_entry>
    <text_entry key="Q2A7">&gt; 60</text_entry>
    <text_entry key="Q3">YOUR GENDER</text_entry>
    <text_entry key="Q3A1">FEMALE</text_entry>
    <text_entry key="Q3A2">MALE</text_entry>
    <text_entry key="Q3A3">OTHER</text_entry>
    <text_entry key="Q4">YOUR BOXING HABITS</text_entry>
    <text_entry key="Q4A1">NEVER</text_entry>
    <text_entry key="Q4A2">LEISURE</text_entry>
    <text_entry key="Q4A3">REGULAR</text_entry>
    <text_entry key="Q4A4">PRO</text_entry>
    <text_entry key="SCREEN4_TITLE">IT’S YOUR TURN TO BOX!</text_entry>
    <text_entry key="SCREEN4_CONTENT">Careful, you don’t need to hit very hard – without gloves you could hurt yourself.
&#13;&#10;The game only calls for mobility and precision.
&#13;&#10;&#13;&#10;Go and stand in front of the luminous punch bag corresponding to your colour. Then hit it at shoulder height to begin.</text_entry>
    <text_entry key="SCREEN6_TITLE">IT’S YOUR TURN TO BOX!</text_entry>
    <text_entry key="SCREEN7_TITLE">SCORE</text_entry>
    <text_entry key="SCREEN7_FINAL_SCORE">Your score</text_entry>
    <text_entry key="SCREEN7_BEST_SCORE">Best score</text_entry>
    <text_entry key="SCREEN7_PRECISION">Precision</text_entry>
    <text_entry key="SCREEN7_SPEED">Reactivity</text_entry>
    <text_entry key="SCREEN7_PTS">pts</text_entry>
    <text_entry key="SCREEN7_THANKS">Thank you for taking part in this activity!</text_entry>
    <text_entry key="COUNTDOWN_GO">GO!</text_entry>
  </lang_text_entries>
</lang_text>